{"key":"cabinet","collectionUrl":"https://elitehubs.com/collections/pc-cabinet","items":[{"name":"LIAN LI O11 Dynamic EATX Mid Tower Cabinet (White)","price":13299,"mrp":16999,"path":"/eh-images/cabinet/lianli-o11-white.jpg"},{"name":"COOLER MASTER Masterbox TD500 Mesh EATX Mid Tower Cabinet (White)","price":7999,"mrp":13000,"path":"/eh-images/cabinet/cm-td500-white.jpg"},{"name":"GAMDIAS Argus E4 Elite ATX Mid Tower Cabinet (White)","price":3844,"mrp":5049,"path":"/eh-images/cabinet/gamdias-argus-e4-white.webp"},{"name":"CORSAIR iCUE 5000X RGB ATX Mid Tower Cabinet (Black)","price":15499,"mrp":19500,"path":"/eh-images/cabinet/corsair-5000x-black.jpg"},{"name":"CORSAIR iCUE 7000X RGB ATX Full Tower Cabinet (Black)","price":29695,"mrp":39000,"path":"/eh-images/cabinet/corsair-7000x-black.webp"},{"name":"COOLER MASTER CMP 520 ATX ARGB Mid Tower Cabinet (Black)","price":5015,"mrp":6499,"path":"/eh-images/cabinet/cm-cmp520-black.jpg"},{"name":"ANT ESPORTS 690 Air ARGB ATX Mid Tower Cabinet (White)","price":6494,"mrp":10299,"path":"/eh-images/cabinet/ant-690-air-white.webp"},{"name":"MSI MAG Forge 111R ARGB ATX Mid Tower Cabinet (Black)","price":2999,"mrp":5949,"path":"/eh-images/cabinet/msi-forge-111r-black.jpg"},{"name":"ANT ESPORTS ICE-320TG RGB ATX Mid Tower Cabinet (Black)","price":2891,"mrp":5999,"path":"/eh-images/cabinet/ant-ice320tg-black.jpg"},{"name":"ANT ESPORTS Graffiti ATX Mid Tower Cabinet (Black)","price":4295,"mrp":8099,"path":"/eh-images/cabinet/ant-graffiti-black.webp"},{"name":"ANT ESPORTS ICE-4000 RGB Mesh ATX Mid Tower Cabinet (Black)","price":5195,"mrp":7599,"path":"/eh-images/cabinet/ant-ice4000-black.webp"},{"name":"ANT ESPORTS 250 Air RGB ATX Mid Tower Cabinet (Black)","price":2800,"mrp":7000,"path":"/eh-images/cabinet/ant-250-air-black.webp"},{"name":"ANT ESPORTS SX5 ARGB ATX Mid Tower Cabinet (Black)","price":3375,"mrp":5199,"path":"/eh-images/cabinet/ant-sx5-black.webp"},{"name":"ANT ESPORTS 200 Air Mini Mesh MATX Mini Tower Cabinet (White)","price":3066,"mrp":6999,"path":"/eh-images/cabinet/ant-200-air-white.webp"},{"name":"CORSAIR 3000D RGB Airflow ATX Mid Tower Cabinet (Black)","price":8395,"mrp":13999,"path":"/eh-images/cabinet/corsair-3000d-black.webp"}]}