{"key":"storage","collectionUrl":"https://elitehubs.com/collections/ssd","items":[{"name":"ADATA XPG Gammix S5 256GB M.2 NVMe Gen3 Solid State Drive (SSD)","price":1905,"mrp":6500,"path":"/eh-images/storage/adata-gammix-s5-256.webp"},{"name":"ADATA XPG SX6000 Pro 256GB M.2 NVMe Gen3 Solid State Drive (SSD)","price":4000,"mrp":8999,"path":"/eh-images/storage/adata-sx6000-pro-256.webp"},{"name":"WESTERN DIGITAL Green 120GB 2.5 SATA Gen 3 Internal Solid State Drive (SSD)","price":2050,"mrp":3100,"path":"/eh-images/storage/wd-green-120-sata.webp"},{"name":"TEAM GROUP T-Force Vulcan Z 256GB 2.5 SATA SATA 3 Solid State Drive (SSD)","price":2015,"mrp":2999,"path":"/eh-images/storage/teamgroup-vulcanz-256.webp"},{"name":"WESTERN DIGITAL Green 240GB M.2 SATA SATA 3 Solid State Drive (SSD)","price":2299,"mrp":4300,"path":"/eh-images/storage/wd-green-240-m2.jpg"},{"name":"SAMSUNG 980 1TB M.2 NVME Gen3 Internal Solid State Drive (SSD)","price":13000,"mrp":16199,"path":"/eh-images/storage/samsung-980-1tb.webp"},{"name":"TEAMGROUP MP33 Pro 1TB M.2 NVME Gen3 Solid State Drive (SSD)","price":5199,"mrp":11125,"path":"/eh-images/storage/teamgroup-mp33-pro-1tb.gif"},{"name":"ADATA XPG Gammix S11 Pro 256GB M.2 NVMe Gen3 Solid State Drive (SSD)","price":2595,"mrp":8000,"path":"/eh-images/storage/adata-s11-pro-256.jpg"},{"name":"TEAM GROUP T-Force Vulcan Z 1TB 2.5 SATA SATA 3 Solid State Drive (SSD)","price":17498,"mrp":17498,"path":"/eh-images/storage/teamgroup-vulcanz-1tb.webp"},{"name":"KINGSTON A400 240GB 2.5 SATA SATA 3 Internal Solid State Drive (SSD)","price":6075,"mrp":6075,"path":"/eh-images/storage/kingston-a400-240.webp"},{"name":"ANT ESPORTS 690 Neo Pro 256GB M.2 NVMe Gen3 Solid State Drive (SSD)","price":2899,"mrp":6499,"path":"/eh-images/storage/ant-690-neo-pro-256.webp"},{"name":"WESTERN DIGITAL Blue SA510 500GB 2.5 SATA SATA 3 Solid State Drive (SSD)","price":8463,"mrp":11900,"path":"/eh-images/storage/wd-blue-sa510-500.webp"},{"name":"CORSAIR MP600 Pro NH 1TB M.2 NVME Gen4 Solid State Drive (SSD)","price":16715,"mrp":19999,"path":"/eh-images/storage/corsair-mp600-pro-nh-1tb.webp"},{"name":"CORSAIR MP600 Pro LPX 1TB M.2 NVME Gen4 Solid State Drive (SSD)","price":15555,"mrp":25999,"path":"/eh-images/storage/corsair-mp600-pro-lpx-1tb.webp"},{"name":"ADATA Legend 710 1TB M.2 NVME Gen3 Internal Solid State Drive (SSD)","price":16755,"mrp":19999,"path":"/eh-images/storage/adata-legend-710-1tb.webp"}]}
